docs/conf.py
pyds8k/__init__.py
pyds8k/base.py
pyds8k/dateutil.py
pyds8k/example.py
pyds8k/exceptions.py
pyds8k/httpclient.py
pyds8k/messages.py
pyds8k/settings.py
pyds8k/size_converter.py
pyds8k/utils.py
pyds8k/auth/__init__.py
pyds8k/auth/authenticate.py
pyds8k/auth/ds8k/__init__.py
pyds8k/auth/ds8k/base.py
pyds8k/auth/ds8k/v1/__init__.py
pyds8k/auth/ds8k/v1/auth.py
pyds8k/client/__init__.py
pyds8k/client/exceptions.py
pyds8k/client/ds8k/__init__.py
pyds8k/client/ds8k/v1/__init__.py
pyds8k/client/ds8k/v1/client.py
pyds8k/client/ds8k/v1/sc_client.py
pyds8k/dataParser/__init__.py
pyds8k/dataParser/base.py
pyds8k/dataParser/ds8k.py
pyds8k/resources/__init__.py
pyds8k/resources/utils.py
pyds8k/resources/ds8k/__init__.py
pyds8k/resources/ds8k/v1/__init__.py
pyds8k/resources/ds8k/v1/encryption_groups.py
pyds8k/resources/ds8k/v1/eserep.py
pyds8k/resources/ds8k/v1/events.py
pyds8k/resources/ds8k/v1/flashcopy.py
pyds8k/resources/ds8k/v1/host_ports.py
pyds8k/resources/ds8k/v1/hosts.py
pyds8k/resources/ds8k/v1/io_enclosures.py
pyds8k/resources/ds8k/v1/ioports.py
pyds8k/resources/ds8k/v1/lss.py
pyds8k/resources/ds8k/v1/mappings.py
pyds8k/resources/ds8k/v1/marrays.py
pyds8k/resources/ds8k/v1/nodes.py
pyds8k/resources/ds8k/v1/pools.py
pyds8k/resources/ds8k/v1/pprc.py
pyds8k/resources/ds8k/v1/resource_groups.py
pyds8k/resources/ds8k/v1/systems.py
pyds8k/resources/ds8k/v1/tserep.py
pyds8k/resources/ds8k/v1/users.py
pyds8k/resources/ds8k/v1/volumes.py
pyds8k/resources/ds8k/v1/common/__init__.py
pyds8k/resources/ds8k/v1/common/attr_names.py
pyds8k/resources/ds8k/v1/common/base.py
pyds8k/resources/ds8k/v1/common/mixins.py
pyds8k/resources/ds8k/v1/common/types.py
pyds8k/resources/ds8k/v1/cs/__init__.py
pyds8k/resources/ds8k/v1/cs/flashcopies.py
pyds8k/resources/ds8k/v1/cs/pprcs.py
pyds8k/resources/ds8k/v1/hmc/__init__.py
pyds8k/resources/ds8k/v1/hmc/hmc.py
pyds8k/resources/ds8k/v1/hmc/restart.py
pyds8k/resources/ds8k/v1/hmc/certificate/__init__.py
pyds8k-1.6.0.dist-info/licenses/LICENSE
pyds8k-1.6.0.dist-info/METADATA
pyds8k-1.6.0.dist-info/WHEEL
pyds8k-1.6.0.dist-info/top_level.txt
pyds8k-1.6.0.dist-info/RECORD
