Metadata-Version: 2.4
Name: pyds8k
Version: 1.6.0
Summary: DS8000 Python Client
Author-email: Zhang Wu <shwzhang@cn.ibm.com>
Maintainer-email: Randy Blea <blead@us.ibm.com>, NjM3MjY5NzAgNzA3MzA3 <102704081+NjM3MjY5NzAgNzA3MzA3@users.noreply.github.com>
Project-URL: Documentation, https://pyds8k.readthedocs.io/en/latest
Project-URL: Homepage, https://github.com/IBM/pyds8k
Project-URL: Issues, https://github.com/IBM/pyds8k/issues
Project-URL: Repository, https://github.com/IBM/pyds8k.git
Keywords: IBM,DS8000 Storage
Classifier: Development Status :: 5 - Production/Stable
Classifier: Intended Audience :: Developers
Classifier: Intended Audience :: System Administrators
Classifier: Environment :: Console
Classifier: Programming Language :: Python
Classifier: Programming Language :: Python :: 3.9
Classifier: Programming Language :: Python :: 3.10
Classifier: Programming Language :: Python :: 3.11
Classifier: Programming Language :: Python :: 3.12
Classifier: Programming Language :: Python :: 3.13
Classifier: Topic :: Software Development :: Libraries :: Python Modules
Requires-Python: >=3.9
License-File: LICENSE
Requires-Dist: requests>=2.32.4
Dynamic: license-file
